thumbor_aws/__init__.py
thumbor_aws/config.py
thumbor_aws/loader.py
thumbor_aws/result_storage.py
thumbor_aws/s3_client.py
thumbor_aws/storage.py
thumbor_aws/utils.py
thumbor_aws-0.9.1.dist-info/LICENSE
thumbor_aws-0.9.1.dist-info/METADATA
thumbor_aws-0.9.1.dist-info/WHEEL
thumbor_aws-0.9.1.dist-info/RECORD
