Metadata-Version: 2.3
Name: thumbor_aws
Version: 0.9.1
Summary: thumbor_aws provides extensions for thumbor using AWS
License: MIT
Keywords: imaging,face,detection,feature,thumbnail,imagemagick,pil,opencv
Author: Bernardo Heynemann
Author-email: heynemann@gmail.com
Requires-Python: >=3.9,<3.14
Classifier: Development Status :: 4 - Beta
Classifier: Intended Audience :: Developers
Classifier: License :: OSI Approved :: MIT License
Classifier: Natural Language :: English
Classifier: Operating System :: MacOS
Classifier: Operating System :: POSIX :: Linux
Classifier: Programming Language :: Python :: 3
Classifier: Programming Language :: Python :: 3.9
Classifier: Programming Language :: Python :: 3.10
Classifier: Programming Language :: Python :: 3.11
Classifier: Programming Language :: Python :: 3.12
Classifier: Programming Language :: Python :: 3.13
Classifier: Programming Language :: Python :: 3 :: Only
Classifier: Topic :: Internet :: WWW/HTTP :: Dynamic Content
Classifier: Topic :: Multimedia :: Graphics :: Presentation
Requires-Dist: aiobotocore (>=2.0,<3.0)
Requires-Dist: deprecated (>=1.2,<2.0)
Requires-Dist: pycurl (>=7.44,<8.0)
Requires-Dist: thumbor (>=7.7,<8.0)
